scry_math/__init__.py
scry_math-0.5.dist-info/DESCRIPTION.rst
scry_math-0.5.dist-info/METADATA
scry_math-0.5.dist-info/RECORD
scry_math-0.5.dist-info/WHEEL
scry_math-0.5.dist-info/metadata.json
scry_math-0.5.dist-info/top_level.txt
