Metadata-Version: 2.0
Name: scry-math
Version: 0.5
Summary: A simple SCRY service to extend SPARQL with basic math procedures
Home-page: http://www.few.vu.nl/
Author: Bas Stringer
Author-email: b.stringer@vu.nl
License: MIT
Keywords: scry sparql math service extension
Platform: UNKNOWN
Classifier: Development Status :: 4 - Beta
Classifier: Intended Audience :: Developers
Classifier: Intended Audience :: Information Technology
Classifier: Intended Audience :: Science/Research
Classifier: License :: OSI Approved :: MIT License
Classifier: Operating System :: OS Independent
Classifier: Programming Language :: Python :: 2
Classifier: Programming Language :: Python :: 2.7
Classifier: Topic :: Scientific/Engineering
Classifier: Topic :: Scientific/Engineering :: Mathematics
Requires-Dist: scipy (>=0.15.0)
Requires-Dist: scry (>=0.1)
